easy_email/__init__.py
easy_email/easy_email.py
dm_easy_email-0.2.3.dist-info/LICENSE.md
dm_easy_email-0.2.3.dist-info/METADATA
dm_easy_email-0.2.3.dist-info/WHEEL
dm_easy_email-0.2.3.dist-info/top_level.txt
dm_easy_email-0.2.3.dist-info/RECORD
