Metadata-Version: 2.1
Name: dm-easy-email
Version: 0.2.3
Summary: Data mining Group develop utils
Home-page: http://gitlab.admin.bluemoon.com.cn/BigData-DataAlgorithm/dm-utils.git
Author: Shenxian Shi
Author-email: shishenxian@bluemoon.com.cn
License: MIT License        
Platform: UNKNOWN
Requires-Python: >=3.7
License-File: LICENSE.md
